[{"id":"26028","наименование":"Саморезы по дереву (с крупной резьбой); с потайной головкой и крестообразным шлицем; черные (фосфатированные) ;  D 3,5 мм; длина 32 мм; 1 кг","категория":null,"свойства":[{"имя":"Вид саморезов","значение":"Саморезы по дереву (с крупной резьбой)","группировка":null},{"имя":"Тип головки саморезов","значение":"с потайной головкой и крестообразным шлицем","группировка":null},{"имя":"Тип покрытия","значение":"черные (фосфатированные) ","группировка":null},{"имя":"Диаметр резьбы","значение":" D 3,5 мм","группировка":null},{"имя":"Длина","значение":"32 мм","группировка":null},{"имя":"Фасовка метизов","значение":"1 кг","группировка":null}],"инфо":null,"синонимы":null,"нормализатор":null}]